pyhailing/__init__.py
pyhailing/core.py
pyhailing/ridehail_env.py
pyhailing/data/lots.csv
pyhailing/data/speeds.csv
pyhailing/data/taxizones.geojson
pyhailing/data/trips.csv
tests/__init__.py
tests/test_ridehail_env.py
pyhailing-0.0.9.dist-info/LICENSE
pyhailing-0.0.9.dist-info/METADATA
pyhailing-0.0.9.dist-info/WHEEL
pyhailing-0.0.9.dist-info/top_level.txt
pyhailing-0.0.9.dist-info/RECORD
