Metadata-Version: 2.1
Name: pyhailing
Version: 0.0.9
Summary: An OpenAI gym environment for a ridehailing application
Home-page: https://github.com/nkullman/ridehailing_package
Author: Nicholas Kullman
Author-email: nick.kullman@gmail.com
License: UNKNOWN
Platform: UNKNOWN
Classifier: Programming Language :: Python
Classifier: Programming Language :: Python :: 3
Classifier: Programming Language :: Python :: 3.7
Classifier: License :: OSI Approved :: Apache Software License
Requires-Python: >=3.7
License-File: LICENSE
Requires-Dist: gym
Requires-Dist: matplotlib
Requires-Dist: numpy (<1.22,>=1.19)
Requires-Dist: pandas
Requires-Dist: Pillow
Requires-Dist: scipy
